smtp2paperless.py
smtp2paperless-0.0.3.dist-info/METADATA
smtp2paperless-0.0.3.dist-info/WHEEL
smtp2paperless-0.0.3.dist-info/entry_points.txt
smtp2paperless-0.0.3.dist-info/top_level.txt
smtp2paperless-0.0.3.dist-info/RECORD
