Metadata-Version: 2.1
Name: smtp2paperless
Version: 0.0.3
Summary: A bridge between SMTP and the Paperless API
Author-email: Matthias Riße <matthias.risze@t-online.de>
License: Apache License
Project-URL: Documentation, https://github.com/matrss/smtp2paperless#readme
Project-URL: Issues, https://github.com/matrss/smtp2paperless/issues
Project-URL: Source, https://github.com/matrss/smtp2paperless
Keywords: paperless-ngx,SMTP
Classifier: License :: OSI Approved :: Apache Software License
Classifier: Programming Language :: Python :: 3
Requires-Python: >=3.8
Requires-Dist: aiosmtpd
Requires-Dist: requests
